Metadata-Version: 2.1
Name: plugin-package-template
Version: 0.1.418442759
Summary: Plugin template project used to quick start development of a new Versatile Data Kit SDK plugin.
Home-page: https://github.com/vmware/versatile-data-kit
License: UNKNOWN
Platform: UNKNOWN
Classifier: Development Status :: 4 - Beta
Classifier: License :: OSI Approved :: Apache Software License
Classifier: Programming Language :: Python :: 3.7
Classifier: Programming Language :: Python :: 3.8
Classifier: Programming Language :: Python :: 3.9
Classifier: Programming Language :: Python :: 3.10
